lm_pub_quiz/__about__.py
lm_pub_quiz/__init__.py
lm_pub_quiz/types.py
lm_pub_quiz/util.py
lm_pub_quiz/data/__init__.py
lm_pub_quiz/data/base.py
lm_pub_quiz/data/dataset.py
lm_pub_quiz/data/results.py
lm_pub_quiz/data/util.py
lm_pub_quiz/evaluators/__init__.py
lm_pub_quiz/evaluators/base.py
lm_pub_quiz/evaluators/model_util.py
lm_pub_quiz/evaluators/pll_evaluators.py
lm_pub_quiz/evaluators/scoring_mixins.py
lm_pub_quiz/evaluators/templating_util.py
lm_pub_quiz/evaluators/tyq_evaluator.py
lm_pub_quiz/evaluators/util.py
lm_pub_quiz/integrations/__init__.py
lm_pub_quiz/integrations/transformers_trainer.py
lm_pub_quiz/metrics/__init__.py
lm_pub_quiz/metrics/base.py
lm_pub_quiz/metrics/basic.py
lm_pub_quiz/metrics/confidence.py
lm_pub_quiz/metrics/util.py
lm_pub_quiz-0.3.3.dist-info/METADATA
lm_pub_quiz-0.3.3.dist-info/WHEEL
lm_pub_quiz-0.3.3.dist-info/licenses/LICENSE
lm_pub_quiz-0.3.3.dist-info/RECORD
