Metadata-Version: 2.4
Name: lm-pub-quiz
Version: 0.3.3
Summary: Evaluate language models using multiple choice items
Author-email: Jacek Wiland <jacek.wiland@hu-berlin.de>, Max Ploner <max.ploner@hu-berlin.de>, Alan Akbik <alan.akbik@hu-berlin.de>
License-File: LICENSE
Classifier: Development Status :: 4 - Beta
Classifier: License :: OSI Approved :: MIT License
Classifier: Operating System :: OS Independent
Classifier: Programming Language :: Python
Classifier: Programming Language :: Python :: 3.9
Classifier: Programming Language :: Python :: 3.10
Classifier: Programming Language :: Python :: 3.11
Classifier: Programming Language :: Python :: 3.12
Classifier: Programming Language :: Python :: 3.13
Requires-Python: >=3.9
Requires-Dist: accelerate>0.25.0
Requires-Dist: datasets
Requires-Dist: numpy
Requires-Dist: pandas
Requires-Dist: scikit-learn
Requires-Dist: torch
Requires-Dist: transformers>=4.38
